licenselib/__init__.py
licenselib/github.py
licenselib/license.py
licenselib/pypi.py
licenselib/utils.py
licenselib-1.0.0.dist-info/LICENSE
licenselib-1.0.0.dist-info/METADATA
licenselib-1.0.0.dist-info/WHEEL
licenselib-1.0.0.dist-info/top_level.txt
licenselib-1.0.0.dist-info/RECORD
