Metadata-Version: 2.1
Name: licenselib
Version: 1.0.0
Summary: Library for fetching licenses and dependencies
License: MIT
Requires-Python: >=3.10
License-File: LICENSE
Requires-Dist: requests
Requires-Dist: pip-licenses
Requires-Dist: pip-licenses-lib
Requires-Dist: pip
